alignerr_tools/__init__.py
alignerr_tools/enums.py
alignerr_tools/models.py
alignerr_tools/project_management.py
alignerr_tools/project_settings.py
alignerr_tools/rates.py
alignerr_tools/user_management.py
alignerr_tools-0.3.0.dist-info/LICENSE
alignerr_tools-0.3.0.dist-info/METADATA
alignerr_tools-0.3.0.dist-info/WHEEL
alignerr_tools-0.3.0.dist-info/RECORD
