Metadata-Version: 2.3
Name: alignerr-tools
Version: 0.3.0
Summary: Tools to manage Alignerr projects
Author: Labelbox Alignerr Team
Author-email: support@labelbox.com
Requires-Python: >=3.9,<3.14
Classifier: Development Status :: 4 - Beta
Classifier: Intended Audience :: Developers
Classifier: License :: OSI Approved :: MIT License
Classifier: Programming Language :: Python :: 3
Classifier: Programming Language :: Python :: 3.9
Classifier: Programming Language :: Python :: 3.10
Classifier: Programming Language :: Python :: 3.11
Classifier: Programming Language :: Python :: 3.12
Classifier: Programming Language :: Python :: 3.13
Requires-Dist: labelbox (>=7.0.0)
Project-URL: Homepage, https://github.com/Labelbox/alignerr-tools
Project-URL: Repository, https://github.com/Labelbox/alignerr-tools
